{
  "job": {
    "title": "Data Scientist",
    "industry": "Hospital &amp; Health Care,Information Technology and Services",
    "description": "",
    "employment_type": "FULL_TIME",
    "date_posted": "2021-08-26T18:52:24.000Z"
  },
  "company": {
    "name": "BETSOL",
    "link": "https://www.linkedin.com/company/betsol"
  },
  "education": {
    "required_credential": "bachelor degree"
  },
  "experience": {
    "months_of_experience": null,
    "seniority_level": null
  },
  "salary": {
    "currency": null,
    "min_value": null,
    "max_value": null,
    "unit": null
  },
  "location": {
    "country": "US",
    "locality": "Oakland",
    "region": "CA",
    "postal_code": "94612",
    "street_address": null,
    "latitude": 37.80483,
    "longitude": -122.27248
  }
}