{
  "job": {
    "title": "Software Engineer",
    "industry": "",
    "description": "ltpgtltstronggtOur CompanyltstronggtltpgtltpgtGenista Biosciences is a rapidly growing biotech startup company based in San Jose CA dedicated to improving public health and food safety both on the community and global scaleltpgtltpgtltbrgtltpgtltpgtltstronggtAbout the Roleltstronggtltpgtltpgt Collaborate with the UXUI design team to ensure that vision is being properly followedltpgtltpgt Implement backend functionalities for inhouse mobile and web applicationsltpgtltpgt Provide ongoing maintenance support and enhancements to the existing platformltpgtltpgt Define front end architecture and components define user experience handle state and clientside experiencesltpgtltpgt Perform integrations tasks of various modules and components that have been developed by other engineersltpgtltpgt Work with the development team to help define system architectureltpgtltpgt Perform rigorous testing and bugfixes on new and existing codeltpgtltpgt Write scriptsprograms for performing testing automating tasks and controlling robotics systemsltpgtltpgtltbrgtltpgtltpgtltstronggtQualificationsltstronggtltpgtltpgt BS or MS in Computer Science Computer Engineering or other technologyrelated fieldltpgtltpgt Experience with either iOS or Android app developmentltpgtltpgt Experience with web technologiesframeworks like React Django and NodeJSltpgtltpgt Preferred Languages JavaScript Java Swift Objective C PythonltpgtltpgtltbrgtltpgtltpgtltstronggtAbout the PositionltstronggtltpgtltpgtThis is a full time position with competitive salary and health vision dental and life insurance benefits that are fully covered by Genista with no outofpocket expenses Additional perks include gym membership free onsite lunch paid vacation and a casual working environmentltpgt",
    "employment_type": "FULL_TIME",
    "date_posted": "2021-08-04T21:46:44.000Z"
  },
  "company": {
    "name": "Genista Biosciences",
    "link": "https://www.linkedin.com/company/genista-biosciences"
  },
  "education": {
    "required_credential": "bachelor degree"
  },
  "experience": {
    "months_of_experience": null,
    "seniority_level": null
  },
  "salary": {
    "currency": null,
    "min_value": null,
    "max_value": null,
    "unit": null
  },
  "location": {
    "country": "US",
    "locality": "San Jose",
    "region": "CA",
    "postal_code": "95148",
    "street_address": null,
    "latitude": 37.334793,
    "longitude": -121.888145
  }
}