{
  "job": {
    "title": "Senior Site Reliability Engineer (Remote)",
    "industry": "Information Technology and Services,Computer Software",
    "description": "strongWork for a great companybrbrstrongThis Jobot Job is hosted by Pegah ShakeribrbrAre you a fit Easy Apply now by clicking the Apply button and sending us your resumebrbrSalary 130000  200000 per yearbrbrstrongA Bit About UsbrbrstrongWere looking for problem solvers innovators and dreamers who are searching for anything but business as usual Like us youre a high performer whos an expert at your craft constantly challenging the status quobrbrstrongbrbrstrongWhy join usbrbrbrstrongstrongPosition OverviewbrbrYoull be working on a new team that will create the observability systems and practice for our Cloud Help build the practice as well as design architect build and manage systems for metrics logs and tracing Youll also be an evangelist with stakeholders on SRE concepts and practices Create a center of excellence for observabilitybrbrstrongJob DetailsbrbrstrongWhat youll dobrbrCreate the observability architecture for metrics logs and tracing systems for our CloudbrbrDesign Manage and operate the observability systembrbrEvangelize tools and practices with engineering architecture and customer service teams as a subject matter expertbrbrBuild dashboards and escalation systems for production engineering customer service and engineering teamsbrbrEnsure stakeholder teams are using the tools in the best way make iterative improvements through problem solving empathy and communicationbrbrstrongAbout Youbrbrstrong4 years expertise with metrics timeseries logging andor distributed tracingbrbrThe team will offer Observability as a servicebrbr3 years experience with building observability systems using products like Elastic Search splunk datadog Prometheus TICK stack Grafana kibana your choicebrbr45 years programming and software development  python java go NET or any other languagebrbr1 or more years experience working with cloud providers like AWS GCP or AzurebrbrWorking knowledge of SDLC conceptsbrbrInterested in hearing more Easy Apply now by clicking the Apply buttonbrbr",
    "employment_type": "FULL_TIME",
    "date_posted": "2021-08-18T21:00:50.000Z"
  },
  "company": {
    "name": "Jobot",
    "link": "https://www.linkedin.com/company/jobot"
  },
  "education": {
    "required_credential": "bachelor degree"
  },
  "experience": {
    "months_of_experience": 60,
    "seniority_level": "Senior"
  },
  "salary": {
    "currency": null,
    "min_value": null,
    "max_value": null,
    "unit": null
  },
  "location": {
    "country": "US",
    "locality": "Jersey City",
    "region": "NJ",
    "postal_code": "07306",
    "street_address": null,
    "latitude": 40.717495,
    "longitude": -74.04411
  }
}