{
  "job": {
    "title": "Senior Data Engineer",
    "industry": "",
    "description": "Position ETL Data Engineer with PostgreSQL ExperiencebrDuration Long TermbrLocation NYC NY  Lake Mary FL Remote work till COVIDbrNo of positions 1brbr12 15 years experience working with data data engineering Design lead  Building Framework and Solutions etc brExperience analyzing and working with large datasets and designing solution a mustbrStrong experience in buildingdesigning reusable solution and framework brProficiency with SQL  10 years experience brStrong experience in PostgreSQL Redshift DBbrStrong experience in working Cloud framework brStrong experience of ETL tools like Informatica PowerCenter 10 years experiencebrStrong experience in IICS  Minimum 2 years experiencebrStrong experience in AWS different components  Must be proficient  in Athena Redshift S3LamdaGlue etcbrExperience using GitHubbrMust be able to both read  understand code as well as feel comfortable using code as a tool for data analysis brExperience using tools like AlteryxbrDemonstrated Critical thinking ability including the ability to define a problem frame it for a broad audience and collaborate with others to formulate solutions brExcellent communication skills brAbility to work independently and as part of a team with proven ability to influence with impact across functions and disciplines brMust be detail oriented brMust be familiar working in agile environmentbr",
    "employment_type": "CONTRACTOR",
    "date_posted": "2021-07-14T17:14:42.000Z"
  },
  "company": {
    "name": "Confidential",
    "link": "https://www.linkedin.com/company/confidentialcompany"
  },
  "education": {
    "required_credential": "bachelor degree"
  },
  "experience": {
    "months_of_experience": 144,
    "seniority_level": "Senior"
  },
  "salary": {
    "currency": null,
    "min_value": null,
    "max_value": null,
    "unit": null
  },
  "location": {
    "country": "US",
    "locality": "United States",
    "region": null,
    "postal_code": "99999",
    "street_address": null,
    "latitude": 39.50355,
    "longitude": -99.0183
  }
}