{
  "job": {
    "title": "Machine Learning/3D Computer Vision Software Engineer",
    "industry": "",
    "description": "ltpgtltstronggtDEVELOP EMBEDDED COMPUTER VISION APPLICATIONS BY DESIGNING DEVELOPING AND TESTING SOFTWARE SOLUTIONS APPLICATIONS INCLUDE REALTIME 3D MODELING AND ARVRltstronggtltpgtltpgtampnbspltpgtltpgtltstronggtSoftware Engineer Job DutiesltstronggtltpgtltulgtltligtDevelop machine learning algorithms and librariesltligtltligtDevelop computer vision algorithms based on both RGB and 3D point cloud dataltligtltligtCreate detailed documentation including design concept flowcharts layouts diagrams chartsltligtltligtCreate structured coding with relevant code commentsltligtltligtWork with customers directly to understand requirements and design system specifications standards and programmingltligtltligtDevelop software solutions by studying information needs conferring with users studying systems flow data usage and work processes investigating problem areas following the software development lifecycleltligtltulgtltpgtltstronggtDesired Skills and ExperienceltstronggtltpgtltulgtltligtltstronggtSkillsampnbspltstronggtampnbspFamiliarity with Agile Project Management general programming skills C C Matlab Java Unity development platform software design data structures strong math background with ability to understand algorithms in complex geometry software debugging software documentation software testing problem solving teamwork software development fundamentals software development process Jira strong passion and professional commitmentltligtltligtltstronggtQualificationsampnbspltstronggtampnbspApplicable degree required with focus on Computer Vision and Machine LearningltligtltligtltstronggtExperienceampnbspltstronggtampnbspMinimum two years of experience preferred but will consider strong recent graduatesltligtltligtltstronggtResidencyltstronggtampnbspMust be currently residing in the USltligtltulgtltpgtltbrgtltpgtltpgtWe are passionately focused on 3D computer vision We are experts in using 3D depth sensor technologies developing innovative 3D computer vision implementations and processor optimization for mobile devices If you have the skills and passion for 3D computer vision come join usltpgt",
    "employment_type": "FULL_TIME",
    "date_posted": "2021-06-23T16:49:33.000Z"
  },
  "company": {
    "name": "VanGogh Imaging",
    "link": "https://www.linkedin.com/company/vangogh-imaging"
  },
  "education": {
    "required_credential": "bachelor degree"
  },
  "experience": {
    "months_of_experience": 24,
    "seniority_level": null
  },
  "salary": {
    "currency": null,
    "min_value": null,
    "max_value": null,
    "unit": null
  },
  "location": {
    "country": "US",
    "locality": "McLean",
    "region": "VA",
    "postal_code": "22101",
    "street_address": null,
    "latitude": 38.93759,
    "longitude": -77.18378
  }
}