{
  "job": {
    "title": "Machine Learning Engineer",
    "industry": "Hospital &amp; Health Care,Information Technology and Services",
    "description": "pstrongPositionstrongnbspMachine Learning EngineerppstrongLocationstrongnbsp100 RemoteppstrongDurationstrongnbsp6month ContracttoHireppstrongStartstrongnbspASAPppnbspppstrongJob DescriptionObjectivestrongppThis will be a 6month contract with fulltime employee conversion This is a 100 remote role where you will be working on an exciting cuttingedge teamnbspThis position develops efficient and scalable data science systems that enable integration of machine learning ML applications into healthcare operations strategy value improvement care advancement patient safety and satisfactionnbspThis position will partner with data scientists application developers data architects and system engineers to recommend and develop ML systems and pipelinesnbspThis position will be responsible for learning recommending and implementing cutting edge machine learning methodologies and tools in creative and novel waysppnbspppThis person would be the tone setter and first one in the Machine Learning Engineer role with their plan to build out a team behind youppnbspppstrongFun Fact about our relationship with this client strongWe have placed half of their data architect team over the last 18 months with GREAT feedback on culture and the leadershipppnbspppstrongQualificationsstrongpulliCI  CD ExperienceliliData Engineering experience full project life cycle deployment to productionliliSome sort of data science exposureliliExperience doing endtoend implementation of an ML pipeline for ML model deploymentliliSQL amp Python experienceliul",
    "employment_type": "CONTRACTOR",
    "date_posted": "2021-08-18T19:02:58.000Z"
  },
  "company": {
    "name": "Medasource",
    "link": "https://www.linkedin.com/company/medasource"
  },
  "education": {
    "required_credential": "bachelor degree"
  },
  "experience": {
    "months_of_experience": null,
    "seniority_level": null
  },
  "salary": {
    "currency": null,
    "min_value": null,
    "max_value": null,
    "unit": null
  },
  "location": {
    "country": "US",
    "locality": "United States",
    "region": null,
    "postal_code": "99999",
    "street_address": null,
    "latitude": 39.50355,
    "longitude": -99.0183
  }
}