{
  "job": {
    "title": "Software Engineer I",
    "industry": "Computer Software,Information Technology and Services",
    "description": "You go all in no matter what you do, and so do we. You want to use your powers for good, and that’s exactly what we do at Lytx®. Our team is made up of hungry, humble, and capable people who are making a difference every day with technology that helps save lives each year.\nWe are seeking a Software Engineer to help accelerate our industry leading Driver Safety/Fleet Management Programs. Our products manage massive amounts of data collected from over 700,000 vehicles worldwide. We use the data and video to derive intelligent insights using Machine Vision and AI. We also track real time telematics for all devices on the network.\n___________\nLytx is powered by cutting-edge technology and Happy People. You want to use your powers for good, and that’s exactly what we do at Lytx. Our team is made up of hungry, humble, and capable people who are making a difference every day with technology that helps save lives each year.",
    "employment_type": "FULL_TIME",
    "date_posted": "2021-08-10T23:03:58.000Z"
  },
  "company": {
    "name": "Lytx, Inc.",
    "link": "https://www.linkedin.com/company/lytxinc"
  },
  "education": {
    "required_credential": "bachelor degree"
  },
  "experience": {
    "months_of_experience": null,
    "seniority_level": null
  },
  "salary": {
    "currency": null,
    "min_value": null,
    "max_value": null,
    "unit": null
  },
  "location": {
    "country": "US",
    "locality": "San Diego",
    "region": "CA",
    "postal_code": "92161",
    "street_address": null,
    "latitude": 32.71576,
    "longitude": -117.16382
  }
}